{
  "main": {
    "id": "5eb2b68cd86ecfbb",
    "type": "split",
    "children": [
      {
        "id": "755e64cc4b5dc6eb",
        "type": "tabs",
        "children": [
          {
            "id": "00573237819be040",
            "type": "leaf",
            "state": {
              "type": "markdown",
              "state": {
                "file": "index.md",
                "mode": "source",
                "source": false
              },
              "icon": "lucide-file",
              "title": "index"
            }
          }
        ]
      }
    ],
    "direction": "vertical"
  },
  "left": {
    "id": "b46fb030ba83b73c",
    "type": "split",
    "children": [
      {
        "id": "b27d1a7e616f36fa",
        "type": "tabs",
        "children": [
          {
            "id": "d25066d56e3fa6b4",
            "type": "leaf",
            "state": {
              "type": "file-explorer",
              "state": {
                "sortOrder": "alphabetical",
                "autoReveal": false
              },
              "icon": "lucide-folder-closed",
              "title": "文件列表"
            }
          },
          {
            "id": "57050c5e3e5cf78c",
            "type": "leaf",
            "state": {
              "type": "search",
              "state": {
                "query": "",
                "matchingCase": false,
                "explainSearch": false,
                "collapseAll": false,
                "extraContext": false,
                "sortOrder": "alphabetical"
              },
              "icon": "lucide-search",
              "title": "搜索"
            }
          },
          {
            "id": "7580bd285e111c5a",
            "type": "leaf",
            "state": {
              "type": "bookmarks",
              "state": {},
              "icon": "lucide-bookmark",
              "title": "书签"
            }
          }
        ]
      }
    ],
    "direction": "horizontal",
    "width": 300
  },
  "right": {
    "id": "0267443e05589172",
    "type": "split",
    "children": [
      {
        "id": "35aa54ad6f8ae038",
        "type": "tabs",
        "children": [
          {
            "id": "d1416dbf814347ee",
            "type": "leaf",
            "state": {
              "type": "backlink",
              "state": {
                "collapseAll": false,
                "extraContext": false,
                "sortOrder": "alphabetical",
                "showSearch": false,
                "searchQuery": "",
                "backlinkCollapsed": false,
                "unlinkedCollapsed": true
              },
              "icon": "links-coming-in",
              "title": "反向链接"
            }
          },
          {
            "id": "5f2f36d737a8b62d",
            "type": "leaf",
            "state": {
              "type": "outgoing-link",
              "state": {
                "file": "欢迎.md",
                "linksCollapsed": false,
                "unlinkedCollapsed": true
              },
              "icon": "links-going-out",
              "title": "欢迎 的出链列表"
            }
          },
          {
            "id": "c482be174b2cc797",
            "type": "leaf",
            "state": {
              "type": "tag",
              "state": {
                "sortOrder": "frequency",
                "useHierarchy": true,
                "showSearch": false,
                "searchQuery": ""
              },
              "icon": "lucide-tags",
              "title": "标签"
            }
          },
          {
            "id": "37a11a7b2adc1b54",
            "type": "leaf",
            "state": {
              "type": "all-properties",
              "state": {
                "sortOrder": "frequency",
                "showSearch": false,
                "searchQuery": ""
              },
              "icon": "lucide-archive",
              "title": "添加笔记属性"
            }
          },
          {
            "id": "12cd18c27371bd94",
            "type": "leaf",
            "state": {
              "type": "outline",
              "state": {
                "file": "欢迎.md",
                "followCursor": false,
                "showSearch": false,
                "searchQuery": ""
              },
              "icon": "lucide-list",
              "title": "欢迎 的大纲"
            }
          },
          {
            "id": "329976786281cc7d",
            "type": "leaf",
            "state": {
              "type": "git-view",
              "state": {},
              "icon": "git-pull-request",
              "title": "Source Control"
            }
          }
        ],
        "currentTab": 5
      }
    ],
    "direction": "horizontal",
    "width": 318.5
  },
  "left-ribbon": {
    "hiddenItems": {
      "switcher:打开快速切换": false,
      "graph:查看关系图谱": false,
      "canvas:新建白板": false,
      "daily-notes:打开/创建今天的日记": false,
      "templates:插入模板": false,
      "command-palette:打开命令面板": false,
      "bases:新建数据库": false,
      "obsidian-git:Open Git source control": false
    }
  },
  "active": "00573237819be040",
  "lastOpenFiles": [
    "index.md",
    "0工具安装配置/0.0工具安装目录.md",
    "未命名.canvas",
    "0工具安装配置",
    "README.md",
    "quartz-blog",
    "新建文件夹",
    "新建 文本文档.txt",
    "欢迎.md"
  ]
}